<annotation>
  <folder>Zebrafish-01-F</folder>
  <filename>000989.jpg</filename>
  <size>
    <width>2704</width>
    <height>1520</height>
    <depth>3</depth>
  </size>
  <object>
    <name>Zebrafish</name>
    <pose>Unspecified</pose>
    <truncated>1</truncated>
    <difficult>0</difficult>
    <bndbox>
      <xmin>2041</xmin>
      <ymin>1254</ymin>
      <xmax>2091</xmax>
      <ymax>1304</ymax>
    </bndbox>
  </object>
  <object>
    <name>Zebrafish</name>
    <pose>Unspecified</pose>
    <truncated>1</truncated>
    <difficult>0</difficult>
    <bndbox>
      <xmin>2120</xmin>
      <ymin>1310</ymin>
      <xmax>2170</xmax>
      <ymax>1360</ymax>
    </bndbox>
  </object>
</annotation>
