<annotation>
  <folder>Zebrafish-01-F</folder>
  <filename>001279.jpg</filename>
  <size>
    <width>2704</width>
    <height>1520</height>
    <depth>3</depth>
  </size>
  <object>
    <name>Zebrafish</name>
    <pose>Unspecified</pose>
    <truncated>0</truncated>
    <difficult>0</difficult>
    <bndbox>
      <xmin>1955</xmin>
      <ymin>1032</ymin>
      <xmax>2005</xmax>
      <ymax>1082</ymax>
    </bndbox>
  </object>
  <object>
    <name>Zebrafish</name>
    <pose>Unspecified</pose>
    <truncated>0</truncated>
    <difficult>0</difficult>
    <bndbox>
      <xmin>2095</xmin>
      <ymin>1313</ymin>
      <xmax>2145</xmax>
      <ymax>1363</ymax>
    </bndbox>
  </object>
</annotation>
