<annotation>
  <folder>Zebrafish-01-F</folder>
  <filename>001262.jpg</filename>
  <size>
    <width>2704</width>
    <height>1520</height>
    <depth>3</depth>
  </size>
  <object>
    <name>Zebrafish</name>
    <pose>Unspecified</pose>
    <truncated>1</truncated>
    <difficult>0</difficult>
    <bndbox>
      <xmin>2113</xmin>
      <ymin>1120</ymin>
      <xmax>2163</xmax>
      <ymax>1170</ymax>
    </bndbox>
  </object>
  <object>
    <name>Zebrafish</name>
    <pose>Unspecified</pose>
    <truncated>1</truncated>
    <difficult>0</difficult>
    <bndbox>
      <xmin>2080</xmin>
      <ymin>1304</ymin>
      <xmax>2130</xmax>
      <ymax>1354</ymax>
    </bndbox>
  </object>
</annotation>
