<annotation>
  <folder>Zebrafish-01-F</folder>
  <filename>001432.jpg</filename>
  <size>
    <width>2704</width>
    <height>1520</height>
    <depth>3</depth>
  </size>
  <object>
    <name>Zebrafish</name>
    <pose>Unspecified</pose>
    <truncated>0</truncated>
    <difficult>0</difficult>
    <bndbox>
      <xmin>2019</xmin>
      <ymin>1202</ymin>
      <xmax>2069</xmax>
      <ymax>1252</ymax>
    </bndbox>
  </object>
  <object>
    <name>Zebrafish</name>
    <pose>Unspecified</pose>
    <truncated>0</truncated>
    <difficult>0</difficult>
    <bndbox>
      <xmin>2040</xmin>
      <ymin>1285</ymin>
      <xmax>2090</xmax>
      <ymax>1335</ymax>
    </bndbox>
  </object>
</annotation>
