<annotation>
  <folder>Zebrafish-01-F</folder>
  <filename>001422.jpg</filename>
  <size>
    <width>2704</width>
    <height>1520</height>
    <depth>3</depth>
  </size>
  <object>
    <name>Zebrafish</name>
    <pose>Unspecified</pose>
    <truncated>1</truncated>
    <difficult>0</difficult>
    <bndbox>
      <xmin>2016</xmin>
      <ymin>1199</ymin>
      <xmax>2066</xmax>
      <ymax>1249</ymax>
    </bndbox>
  </object>
  <object>
    <name>Zebrafish</name>
    <pose>Unspecified</pose>
    <truncated>1</truncated>
    <difficult>0</difficult>
    <bndbox>
      <xmin>2114</xmin>
      <ymin>1292</ymin>
      <xmax>2164</xmax>
      <ymax>1342</ymax>
    </bndbox>
  </object>
</annotation>
