<annotation>
  <folder>Zebrafish-01-F</folder>
  <filename>001690.jpg</filename>
  <size>
    <width>2704</width>
    <height>1520</height>
    <depth>3</depth>
  </size>
  <object>
    <name>Zebrafish</name>
    <pose>Unspecified</pose>
    <truncated>1</truncated>
    <difficult>0</difficult>
    <bndbox>
      <xmin>1998</xmin>
      <ymin>1244</ymin>
      <xmax>2048</xmax>
      <ymax>1294</ymax>
    </bndbox>
  </object>
  <object>
    <name>Zebrafish</name>
    <pose>Unspecified</pose>
    <truncated>1</truncated>
    <difficult>0</difficult>
    <bndbox>
      <xmin>2113</xmin>
      <ymin>1306</ymin>
      <xmax>2163</xmax>
      <ymax>1356</ymax>
    </bndbox>
  </object>
</annotation>
