<annotation>
  <folder>Zebrafish-01-F</folder>
  <filename>002588.jpg</filename>
  <size>
    <width>2704</width>
    <height>1520</height>
    <depth>3</depth>
  </size>
  <object>
    <name>Zebrafish</name>
    <pose>Unspecified</pose>
    <truncated>0</truncated>
    <difficult>0</difficult>
    <bndbox>
      <xmin>1932</xmin>
      <ymin>1131</ymin>
      <xmax>1982</xmax>
      <ymax>1181</ymax>
    </bndbox>
  </object>
  <object>
    <name>Zebrafish</name>
    <pose>Unspecified</pose>
    <truncated>0</truncated>
    <difficult>0</difficult>
    <bndbox>
      <xmin>1998</xmin>
      <ymin>1080</ymin>
      <xmax>2048</xmax>
      <ymax>1130</ymax>
    </bndbox>
  </object>
</annotation>
