<annotation>
  <folder>Zebrafish-01-F</folder>
  <filename>004424.jpg</filename>
  <size>
    <width>2704</width>
    <height>1520</height>
    <depth>3</depth>
  </size>
  <object>
    <name>Zebrafish</name>
    <pose>Unspecified</pose>
    <truncated>1</truncated>
    <difficult>0</difficult>
    <bndbox>
      <xmin>932</xmin>
      <ymin>781</ymin>
      <xmax>982</xmax>
      <ymax>831</ymax>
    </bndbox>
  </object>
  <object>
    <name>Zebrafish</name>
    <pose>Unspecified</pose>
    <truncated>1</truncated>
    <difficult>0</difficult>
    <bndbox>
      <xmin>801</xmin>
      <ymin>850</ymin>
      <xmax>851</xmax>
      <ymax>900</ymax>
    </bndbox>
  </object>
</annotation>
