<annotation>
  <folder>Zebrafish-01-F</folder>
  <filename>004729.jpg</filename>
  <size>
    <width>2704</width>
    <height>1520</height>
    <depth>3</depth>
  </size>
  <object>
    <name>Zebrafish</name>
    <pose>Unspecified</pose>
    <truncated>1</truncated>
    <difficult>0</difficult>
    <bndbox>
      <xmin>555</xmin>
      <ymin>1252</ymin>
      <xmax>605</xmax>
      <ymax>1302</ymax>
    </bndbox>
  </object>
  <object>
    <name>Zebrafish</name>
    <pose>Unspecified</pose>
    <truncated>1</truncated>
    <difficult>0</difficult>
    <bndbox>
      <xmin>692</xmin>
      <ymin>1269</ymin>
      <xmax>742</xmax>
      <ymax>1319</ymax>
    </bndbox>
  </object>
</annotation>
