<annotation>
  <folder>Zebrafish-01-F</folder>
  <filename>004928.jpg</filename>
  <size>
    <width>2704</width>
    <height>1520</height>
    <depth>3</depth>
  </size>
  <object>
    <name>Zebrafish</name>
    <pose>Unspecified</pose>
    <truncated>1</truncated>
    <difficult>0</difficult>
    <bndbox>
      <xmin>595</xmin>
      <ymin>1073</ymin>
      <xmax>645</xmax>
      <ymax>1123</ymax>
    </bndbox>
  </object>
  <object>
    <name>Zebrafish</name>
    <pose>Unspecified</pose>
    <truncated>1</truncated>
    <difficult>0</difficult>
    <bndbox>
      <xmin>609</xmin>
      <ymin>1113</ymin>
      <xmax>659</xmax>
      <ymax>1163</ymax>
    </bndbox>
  </object>
</annotation>
