<annotation>
  <folder>Zebrafish-01-F</folder>
  <filename>005271.jpg</filename>
  <size>
    <width>2704</width>
    <height>1520</height>
    <depth>3</depth>
  </size>
  <object>
    <name>Zebrafish</name>
    <pose>Unspecified</pose>
    <truncated>0</truncated>
    <difficult>0</difficult>
    <bndbox>
      <xmin>784</xmin>
      <ymin>1170</ymin>
      <xmax>834</xmax>
      <ymax>1220</ymax>
    </bndbox>
  </object>
  <object>
    <name>Zebrafish</name>
    <pose>Unspecified</pose>
    <truncated>0</truncated>
    <difficult>0</difficult>
    <bndbox>
      <xmin>483</xmin>
      <ymin>1165</ymin>
      <xmax>533</xmax>
      <ymax>1215</ymax>
    </bndbox>
  </object>
</annotation>
