<annotation>
  <folder>Zebrafish-01-F</folder>
  <filename>005948.jpg</filename>
  <size>
    <width>2704</width>
    <height>1520</height>
    <depth>3</depth>
  </size>
  <object>
    <name>Zebrafish</name>
    <pose>Unspecified</pose>
    <truncated>0</truncated>
    <difficult>0</difficult>
    <bndbox>
      <xmin>1108</xmin>
      <ymin>825</ymin>
      <xmax>1158</xmax>
      <ymax>875</ymax>
    </bndbox>
  </object>
  <object>
    <name>Zebrafish</name>
    <pose>Unspecified</pose>
    <truncated>0</truncated>
    <difficult>0</difficult>
    <bndbox>
      <xmin>1388</xmin>
      <ymin>824</ymin>
      <xmax>1438</xmax>
      <ymax>874</ymax>
    </bndbox>
  </object>
</annotation>
