<annotation>
  <folder>Zebrafish-01-F</folder>
  <filename>006098.jpg</filename>
  <size>
    <width>2704</width>
    <height>1520</height>
    <depth>3</depth>
  </size>
  <object>
    <name>Zebrafish</name>
    <pose>Unspecified</pose>
    <truncated>0</truncated>
    <difficult>0</difficult>
    <bndbox>
      <xmin>868</xmin>
      <ymin>506</ymin>
      <xmax>918</xmax>
      <ymax>556</ymax>
    </bndbox>
  </object>
  <object>
    <name>Zebrafish</name>
    <pose>Unspecified</pose>
    <truncated>0</truncated>
    <difficult>0</difficult>
    <bndbox>
      <xmin>918</xmin>
      <ymin>520</ymin>
      <xmax>968</xmax>
      <ymax>570</ymax>
    </bndbox>
  </object>
</annotation>
