<annotation>
  <folder>Zebrafish-01-F</folder>
  <filename>006016.jpg</filename>
  <size>
    <width>2704</width>
    <height>1520</height>
    <depth>3</depth>
  </size>
  <object>
    <name>Zebrafish</name>
    <pose>Unspecified</pose>
    <truncated>0</truncated>
    <difficult>0</difficult>
    <bndbox>
      <xmin>971</xmin>
      <ymin>627</ymin>
      <xmax>1021</xmax>
      <ymax>677</ymax>
    </bndbox>
  </object>
  <object>
    <name>Zebrafish</name>
    <pose>Unspecified</pose>
    <truncated>0</truncated>
    <difficult>0</difficult>
    <bndbox>
      <xmin>1095</xmin>
      <ymin>680</ymin>
      <xmax>1145</xmax>
      <ymax>730</ymax>
    </bndbox>
  </object>
</annotation>
