<annotation>
  <folder>Zebrafish-01-F</folder>
  <filename>006328.jpg</filename>
  <size>
    <width>2704</width>
    <height>1520</height>
    <depth>3</depth>
  </size>
  <object>
    <name>Zebrafish</name>
    <pose>Unspecified</pose>
    <truncated>0</truncated>
    <difficult>0</difficult>
    <bndbox>
      <xmin>701</xmin>
      <ymin>646</ymin>
      <xmax>751</xmax>
      <ymax>696</ymax>
    </bndbox>
  </object>
  <object>
    <name>Zebrafish</name>
    <pose>Unspecified</pose>
    <truncated>0</truncated>
    <difficult>0</difficult>
    <bndbox>
      <xmin>616</xmin>
      <ymin>833</ymin>
      <xmax>666</xmax>
      <ymax>883</ymax>
    </bndbox>
  </object>
</annotation>
