<annotation>
  <folder>Zebrafish-02-F</folder>
  <filename>000276.jpg</filename>
  <size>
    <width>2704</width>
    <height>1520</height>
    <depth>3</depth>
  </size>
  <object>
    <name>Zebrafish</name>
    <pose>Unspecified</pose>
    <truncated>1</truncated>
    <difficult>0</difficult>
    <bndbox>
      <xmin>1428</xmin>
      <ymin>664</ymin>
      <xmax>1478</xmax>
      <ymax>714</ymax>
    </bndbox>
  </object>
  <object>
    <name>Zebrafish</name>
    <pose>Unspecified</pose>
    <truncated>0</truncated>
    <difficult>0</difficult>
    <bndbox>
      <xmin>1414</xmin>
      <ymin>575</ymin>
      <xmax>1464</xmax>
      <ymax>625</ymax>
    </bndbox>
  </object>
  <object>
    <name>Zebrafish</name>
    <pose>Unspecified</pose>
    <truncated>0</truncated>
    <difficult>0</difficult>
    <bndbox>
      <xmin>1515</xmin>
      <ymin>1000</ymin>
      <xmax>1565</xmax>
      <ymax>1050</ymax>
    </bndbox>
  </object>
  <object>
    <name>Zebrafish</name>
    <pose>Unspecified</pose>
    <truncated>0</truncated>
    <difficult>0</difficult>
    <bndbox>
      <xmin>1472</xmin>
      <ymin>743</ymin>
      <xmax>1522</xmax>
      <ymax>793</ymax>
    </bndbox>
  </object>
  <object>
    <name>Zebrafish</name>
    <pose>Unspecified</pose>
    <truncated>1</truncated>
    <difficult>0</difficult>
    <bndbox>
      <xmin>1588</xmin>
      <ymin>692</ymin>
      <xmax>1638</xmax>
      <ymax>742</ymax>
    </bndbox>
  </object>
</annotation>
