<annotation>
  <folder>Zebrafish-02-F</folder>
  <filename>000356.jpg</filename>
  <size>
    <width>2704</width>
    <height>1520</height>
    <depth>3</depth>
  </size>
  <object>
    <name>Zebrafish</name>
    <pose>Unspecified</pose>
    <truncated>1</truncated>
    <difficult>0</difficult>
    <bndbox>
      <xmin>1657</xmin>
      <ymin>643</ymin>
      <xmax>1707</xmax>
      <ymax>693</ymax>
    </bndbox>
  </object>
  <object>
    <name>Zebrafish</name>
    <pose>Unspecified</pose>
    <truncated>1</truncated>
    <difficult>0</difficult>
    <bndbox>
      <xmin>1786</xmin>
      <ymin>545</ymin>
      <xmax>1836</xmax>
      <ymax>595</ymax>
    </bndbox>
  </object>
  <object>
    <name>Zebrafish</name>
    <pose>Unspecified</pose>
    <truncated>0</truncated>
    <difficult>0</difficult>
    <bndbox>
      <xmin>1333</xmin>
      <ymin>924</ymin>
      <xmax>1383</xmax>
      <ymax>974</ymax>
    </bndbox>
  </object>
  <object>
    <name>Zebrafish</name>
    <pose>Unspecified</pose>
    <truncated>0</truncated>
    <difficult>0</difficult>
    <bndbox>
      <xmin>998</xmin>
      <ymin>772</ymin>
      <xmax>1048</xmax>
      <ymax>822</ymax>
    </bndbox>
  </object>
  <object>
    <name>Zebrafish</name>
    <pose>Unspecified</pose>
    <truncated>0</truncated>
    <difficult>0</difficult>
    <bndbox>
      <xmin>1819</xmin>
      <ymin>798</ymin>
      <xmax>1869</xmax>
      <ymax>848</ymax>
    </bndbox>
  </object>
</annotation>
