<annotation>
  <folder>Zebrafish-02-F</folder>
  <filename>000305.jpg</filename>
  <size>
    <width>2704</width>
    <height>1520</height>
    <depth>3</depth>
  </size>
  <object>
    <name>Zebrafish</name>
    <pose>Unspecified</pose>
    <truncated>1</truncated>
    <difficult>0</difficult>
    <bndbox>
      <xmin>1585</xmin>
      <ymin>622</ymin>
      <xmax>1635</xmax>
      <ymax>672</ymax>
    </bndbox>
  </object>
  <object>
    <name>Zebrafish</name>
    <pose>Unspecified</pose>
    <truncated>1</truncated>
    <difficult>0</difficult>
    <bndbox>
      <xmin>1552</xmin>
      <ymin>574</ymin>
      <xmax>1602</xmax>
      <ymax>624</ymax>
    </bndbox>
  </object>
  <object>
    <name>Zebrafish</name>
    <pose>Unspecified</pose>
    <truncated>0</truncated>
    <difficult>0</difficult>
    <bndbox>
      <xmin>1615</xmin>
      <ymin>1065</ymin>
      <xmax>1665</xmax>
      <ymax>1115</ymax>
    </bndbox>
  </object>
  <object>
    <name>Zebrafish</name>
    <pose>Unspecified</pose>
    <truncated>1</truncated>
    <difficult>0</difficult>
    <bndbox>
      <xmin>1264</xmin>
      <ymin>758</ymin>
      <xmax>1314</xmax>
      <ymax>808</ymax>
    </bndbox>
  </object>
  <object>
    <name>Zebrafish</name>
    <pose>Unspecified</pose>
    <truncated>1</truncated>
    <difficult>0</difficult>
    <bndbox>
      <xmin>1693</xmin>
      <ymin>690</ymin>
      <xmax>1743</xmax>
      <ymax>740</ymax>
    </bndbox>
  </object>
</annotation>
