<annotation>
  <folder>Zebrafish-02-F</folder>
  <filename>000720.jpg</filename>
  <size>
    <width>2704</width>
    <height>1520</height>
    <depth>3</depth>
  </size>
  <object>
    <name>Zebrafish</name>
    <pose>Unspecified</pose>
    <truncated>0</truncated>
    <difficult>0</difficult>
    <bndbox>
      <xmin>1622</xmin>
      <ymin>1173</ymin>
      <xmax>1672</xmax>
      <ymax>1223</ymax>
    </bndbox>
  </object>
  <object>
    <name>Zebrafish</name>
    <pose>Unspecified</pose>
    <truncated>1</truncated>
    <difficult>0</difficult>
    <bndbox>
      <xmin>1918</xmin>
      <ymin>1189</ymin>
      <xmax>1968</xmax>
      <ymax>1239</ymax>
    </bndbox>
  </object>
  <object>
    <name>Zebrafish</name>
    <pose>Unspecified</pose>
    <truncated>1</truncated>
    <difficult>0</difficult>
    <bndbox>
      <xmin>1943</xmin>
      <ymin>1236</ymin>
      <xmax>1993</xmax>
      <ymax>1286</ymax>
    </bndbox>
  </object>
  <object>
    <name>Zebrafish</name>
    <pose>Unspecified</pose>
    <truncated>0</truncated>
    <difficult>0</difficult>
    <bndbox>
      <xmin>1534</xmin>
      <ymin>796</ymin>
      <xmax>1584</xmax>
      <ymax>846</ymax>
    </bndbox>
  </object>
  <object>
    <name>Zebrafish</name>
    <pose>Unspecified</pose>
    <truncated>1</truncated>
    <difficult>0</difficult>
    <bndbox>
      <xmin>1881</xmin>
      <ymin>1183</ymin>
      <xmax>1931</xmax>
      <ymax>1233</ymax>
    </bndbox>
  </object>
</annotation>
