<annotation>
  <folder>Zebrafish-01-T</folder>
  <filename>000240.jpg</filename>
  <size>
    <width>2704</width>
    <height>1520</height>
    <depth>3</depth>
  </size>
  <object>
    <name>Zebrafish</name>
    <pose>Unspecified</pose>
    <truncated>1</truncated>
    <difficult>0</difficult>
    <bndbox>
      <xmin>1591</xmin>
      <ymin>1253</ymin>
      <xmax>1616</xmax>
      <ymax>1278</ymax>
    </bndbox>
  </object>
  <object>
    <name>Zebrafish</name>
    <pose>Unspecified</pose>
    <truncated>1</truncated>
    <difficult>0</difficult>
    <bndbox>
      <xmin>1584</xmin>
      <ymin>1262</ymin>
      <xmax>1609</xmax>
      <ymax>1287</ymax>
    </bndbox>
  </object>
</annotation>
