<annotation>
  <folder>Zebrafish-01-T</folder>
  <filename>002923.jpg</filename>
  <size>
    <width>2704</width>
    <height>1520</height>
    <depth>3</depth>
  </size>
  <object>
    <name>Zebrafish</name>
    <pose>Unspecified</pose>
    <truncated>0</truncated>
    <difficult>0</difficult>
    <bndbox>
      <xmin>1704</xmin>
      <ymin>501</ymin>
      <xmax>1729</xmax>
      <ymax>526</ymax>
    </bndbox>
  </object>
  <object>
    <name>Zebrafish</name>
    <pose>Unspecified</pose>
    <truncated>0</truncated>
    <difficult>0</difficult>
    <bndbox>
      <xmin>1755</xmin>
      <ymin>348</ymin>
      <xmax>1780</xmax>
      <ymax>373</ymax>
    </bndbox>
  </object>
</annotation>
