<annotation>
  <folder>Zebrafish-01-T</folder>
  <filename>003225.jpg</filename>
  <size>
    <width>2704</width>
    <height>1520</height>
    <depth>3</depth>
  </size>
  <object>
    <name>Zebrafish</name>
    <pose>Unspecified</pose>
    <truncated>0</truncated>
    <difficult>0</difficult>
    <bndbox>
      <xmin>1661</xmin>
      <ymin>1190</ymin>
      <xmax>1686</xmax>
      <ymax>1215</ymax>
    </bndbox>
  </object>
  <object>
    <name>Zebrafish</name>
    <pose>Unspecified</pose>
    <truncated>0</truncated>
    <difficult>0</difficult>
    <bndbox>
      <xmin>1616</xmin>
      <ymin>1054</ymin>
      <xmax>1641</xmax>
      <ymax>1079</ymax>
    </bndbox>
  </object>
</annotation>
