<annotation>
  <folder>Zebrafish-01-T</folder>
  <filename>004054.jpg</filename>
  <size>
    <width>2704</width>
    <height>1520</height>
    <depth>3</depth>
  </size>
  <object>
    <name>Zebrafish</name>
    <pose>Unspecified</pose>
    <truncated>1</truncated>
    <difficult>0</difficult>
    <bndbox>
      <xmin>1087</xmin>
      <ymin>1329</ymin>
      <xmax>1112</xmax>
      <ymax>1354</ymax>
    </bndbox>
  </object>
  <object>
    <name>Zebrafish</name>
    <pose>Unspecified</pose>
    <truncated>1</truncated>
    <difficult>0</difficult>
    <bndbox>
      <xmin>897</xmin>
      <ymin>1303</ymin>
      <xmax>922</xmax>
      <ymax>1328</ymax>
    </bndbox>
  </object>
</annotation>
