<annotation>
  <folder>Zebrafish-01-T</folder>
  <filename>007058.jpg</filename>
  <size>
    <width>2704</width>
    <height>1520</height>
    <depth>3</depth>
  </size>
  <object>
    <name>Zebrafish</name>
    <pose>Unspecified</pose>
    <truncated>0</truncated>
    <difficult>0</difficult>
    <bndbox>
      <xmin>1442</xmin>
      <ymin>1234</ymin>
      <xmax>1467</xmax>
      <ymax>1259</ymax>
    </bndbox>
  </object>
  <object>
    <name>Zebrafish</name>
    <pose>Unspecified</pose>
    <truncated>0</truncated>
    <difficult>0</difficult>
    <bndbox>
      <xmin>1410</xmin>
      <ymin>1234</ymin>
      <xmax>1435</xmax>
      <ymax>1259</ymax>
    </bndbox>
  </object>
</annotation>
