<annotation>
  <folder>Zebrafish-01-F</folder>
  <filename>001177.jpg</filename>
  <size>
    <width>2704</width>
    <height>1520</height>
    <depth>3</depth>
  </size>
  <object>
    <name>Zebrafish</name>
    <pose>Unspecified</pose>
    <truncated>0</truncated>
    <difficult>0</difficult>
    <bndbox>
      <xmin>1838</xmin>
      <ymin>1189</ymin>
      <xmax>2030</xmax>
      <ymax>1317</ymax>
    </bndbox>
  </object>
  <object>
    <name>Zebrafish</name>
    <pose>Unspecified</pose>
    <truncated>0</truncated>
    <difficult>0</difficult>
    <bndbox>
      <xmin>2003</xmin>
      <ymin>1271</ymin>
      <xmax>2168</xmax>
      <ymax>1360</ymax>
    </bndbox>
  </object>
</annotation>
