<annotation>
  <folder>Zebrafish-01-F</folder>
  <filename>001102.jpg</filename>
  <size>
    <width>2704</width>
    <height>1520</height>
    <depth>3</depth>
  </size>
  <object>
    <name>Zebrafish</name>
    <pose>Unspecified</pose>
    <truncated>1</truncated>
    <difficult>0</difficult>
    <bndbox>
      <xmin>1986</xmin>
      <ymin>1266</ymin>
      <xmax>2087</xmax>
      <ymax>1335</ymax>
    </bndbox>
  </object>
  <object>
    <name>Zebrafish</name>
    <pose>Unspecified</pose>
    <truncated>1</truncated>
    <difficult>0</difficult>
    <bndbox>
      <xmin>1899</xmin>
      <ymin>1196</ymin>
      <xmax>2142</xmax>
      <ymax>1311</ymax>
    </bndbox>
  </object>
</annotation>
