<annotation>
  <folder>Zebrafish-01-F</folder>
  <filename>002160.jpg</filename>
  <size>
    <width>2704</width>
    <height>1520</height>
    <depth>3</depth>
  </size>
  <object>
    <name>Zebrafish</name>
    <pose>Unspecified</pose>
    <truncated>0</truncated>
    <difficult>0</difficult>
    <bndbox>
      <xmin>1965</xmin>
      <ymin>1094</ymin>
      <xmax>2176</xmax>
      <ymax>1278</ymax>
    </bndbox>
  </object>
  <object>
    <name>Zebrafish</name>
    <pose>Unspecified</pose>
    <truncated>0</truncated>
    <difficult>0</difficult>
    <bndbox>
      <xmin>1937</xmin>
      <ymin>1069</ymin>
      <xmax>2077</xmax>
      <ymax>1154</ymax>
    </bndbox>
  </object>
</annotation>
