<annotation>
  <folder>Zebrafish-01-F</folder>
  <filename>002244.jpg</filename>
  <size>
    <width>2704</width>
    <height>1520</height>
    <depth>3</depth>
  </size>
  <object>
    <name>Zebrafish</name>
    <pose>Unspecified</pose>
    <truncated>0</truncated>
    <difficult>0</difficult>
    <bndbox>
      <xmin>2087</xmin>
      <ymin>809</ymin>
      <xmax>2218</xmax>
      <ymax>902</ymax>
    </bndbox>
  </object>
  <object>
    <name>Zebrafish</name>
    <pose>Unspecified</pose>
    <truncated>0</truncated>
    <difficult>0</difficult>
    <bndbox>
      <xmin>2022</xmin>
      <ymin>1181</ymin>
      <xmax>2202</xmax>
      <ymax>1294</ymax>
    </bndbox>
  </object>
</annotation>
