<annotation>
  <folder>Zebrafish-01-F</folder>
  <filename>002998.jpg</filename>
  <size>
    <width>2704</width>
    <height>1520</height>
    <depth>3</depth>
  </size>
  <object>
    <name>Zebrafish</name>
    <pose>Unspecified</pose>
    <truncated>0</truncated>
    <difficult>0</difficult>
    <bndbox>
      <xmin>1702</xmin>
      <ymin>733</ymin>
      <xmax>1802</xmax>
      <ymax>790</ymax>
    </bndbox>
  </object>
  <object>
    <name>Zebrafish</name>
    <pose>Unspecified</pose>
    <truncated>0</truncated>
    <difficult>0</difficult>
    <bndbox>
      <xmin>1757</xmin>
      <ymin>795</ymin>
      <xmax>1833</xmax>
      <ymax>852</ymax>
    </bndbox>
  </object>
</annotation>
