<annotation>
  <folder>Zebrafish-01-F</folder>
  <filename>003500.jpg</filename>
  <size>
    <width>2704</width>
    <height>1520</height>
    <depth>3</depth>
  </size>
  <object>
    <name>Zebrafish</name>
    <pose>Unspecified</pose>
    <truncated>1</truncated>
    <difficult>0</difficult>
    <bndbox>
      <xmin>1393</xmin>
      <ymin>1101</ymin>
      <xmax>1646</xmax>
      <ymax>1195</ymax>
    </bndbox>
  </object>
  <object>
    <name>Zebrafish</name>
    <pose>Unspecified</pose>
    <truncated>1</truncated>
    <difficult>0</difficult>
    <bndbox>
      <xmin>1423</xmin>
      <ymin>1067</ymin>
      <xmax>1578</xmax>
      <ymax>1143</ymax>
    </bndbox>
  </object>
</annotation>
