<annotation>
  <folder>Zebrafish-01-F</folder>
  <filename>003769.jpg</filename>
  <size>
    <width>2704</width>
    <height>1520</height>
    <depth>3</depth>
  </size>
  <object>
    <name>Zebrafish</name>
    <pose>Unspecified</pose>
    <truncated>0</truncated>
    <difficult>0</difficult>
    <bndbox>
      <xmin>768</xmin>
      <ymin>1058</ymin>
      <xmax>971</xmax>
      <ymax>1137</ymax>
    </bndbox>
  </object>
  <object>
    <name>Zebrafish</name>
    <pose>Unspecified</pose>
    <truncated>0</truncated>
    <difficult>0</difficult>
    <bndbox>
      <xmin>950</xmin>
      <ymin>997</ymin>
      <xmax>1163</xmax>
      <ymax>1067</ymax>
    </bndbox>
  </object>
</annotation>
