<annotation>
  <folder>Zebrafish-01-F</folder>
  <filename>004808.jpg</filename>
  <size>
    <width>2704</width>
    <height>1520</height>
    <depth>3</depth>
  </size>
  <object>
    <name>Zebrafish</name>
    <pose>Unspecified</pose>
    <truncated>1</truncated>
    <difficult>0</difficult>
    <bndbox>
      <xmin>518</xmin>
      <ymin>1150</ymin>
      <xmax>699</xmax>
      <ymax>1309</ymax>
    </bndbox>
  </object>
  <object>
    <name>Zebrafish</name>
    <pose>Unspecified</pose>
    <truncated>1</truncated>
    <difficult>0</difficult>
    <bndbox>
      <xmin>472</xmin>
      <ymin>1280</ymin>
      <xmax>669</xmax>
      <ymax>1363</ymax>
    </bndbox>
  </object>
</annotation>
