<annotation>
  <folder>Zebrafish-01-F</folder>
  <filename>004885.jpg</filename>
  <size>
    <width>2704</width>
    <height>1520</height>
    <depth>3</depth>
  </size>
  <object>
    <name>Zebrafish</name>
    <pose>Unspecified</pose>
    <truncated>0</truncated>
    <difficult>0</difficult>
    <bndbox>
      <xmin>548</xmin>
      <ymin>1175</ymin>
      <xmax>648</xmax>
      <ymax>1294</ymax>
    </bndbox>
  </object>
  <object>
    <name>Zebrafish</name>
    <pose>Unspecified</pose>
    <truncated>0</truncated>
    <difficult>0</difficult>
    <bndbox>
      <xmin>614</xmin>
      <ymin>1080</ymin>
      <xmax>709</xmax>
      <ymax>1212</ymax>
    </bndbox>
  </object>
</annotation>
