<annotation>
  <folder>Zebrafish-01-F</folder>
  <filename>005686.jpg</filename>
  <size>
    <width>2704</width>
    <height>1520</height>
    <depth>3</depth>
  </size>
  <object>
    <name>Zebrafish</name>
    <pose>Unspecified</pose>
    <truncated>0</truncated>
    <difficult>0</difficult>
    <bndbox>
      <xmin>800</xmin>
      <ymin>1116</ymin>
      <xmax>1028</xmax>
      <ymax>1214</ymax>
    </bndbox>
  </object>
  <object>
    <name>Zebrafish</name>
    <pose>Unspecified</pose>
    <truncated>0</truncated>
    <difficult>0</difficult>
    <bndbox>
      <xmin>792</xmin>
      <ymin>1039</ymin>
      <xmax>965</xmax>
      <ymax>1129</ymax>
    </bndbox>
  </object>
</annotation>
