<annotation>
  <folder>Zebrafish-01-F</folder>
  <filename>006706.jpg</filename>
  <size>
    <width>2704</width>
    <height>1520</height>
    <depth>3</depth>
  </size>
  <object>
    <name>Zebrafish</name>
    <pose>Unspecified</pose>
    <truncated>0</truncated>
    <difficult>0</difficult>
    <bndbox>
      <xmin>1272</xmin>
      <ymin>1182</ymin>
      <xmax>1535</xmax>
      <ymax>1263</ymax>
    </bndbox>
  </object>
  <object>
    <name>Zebrafish</name>
    <pose>Unspecified</pose>
    <truncated>0</truncated>
    <difficult>0</difficult>
    <bndbox>
      <xmin>951</xmin>
      <ymin>1191</ymin>
      <xmax>1175</xmax>
      <ymax>1296</ymax>
    </bndbox>
  </object>
</annotation>
