<annotation>
  <folder>Zebrafish-02-F</folder>
  <filename>000005.jpg</filename>
  <size>
    <width>2704</width>
    <height>1520</height>
    <depth>3</depth>
  </size>
  <object>
    <name>Zebrafish</name>
    <pose>Unspecified</pose>
    <truncated>0</truncated>
    <difficult>0</difficult>
    <bndbox>
      <xmin>955</xmin>
      <ymin>669</ymin>
      <xmax>1223</xmax>
      <ymax>811</ymax>
    </bndbox>
  </object>
  <object>
    <name>Zebrafish</name>
    <pose>Unspecified</pose>
    <truncated>0</truncated>
    <difficult>0</difficult>
    <bndbox>
      <xmin>661</xmin>
      <ymin>665</ymin>
      <xmax>754</xmax>
      <ymax>755</ymax>
    </bndbox>
  </object>
  <object>
    <name>Zebrafish</name>
    <pose>Unspecified</pose>
    <truncated>1</truncated>
    <difficult>0</difficult>
    <bndbox>
      <xmin>771</xmin>
      <ymin>525</ymin>
      <xmax>1038</xmax>
      <ymax>658</ymax>
    </bndbox>
  </object>
  <object>
    <name>Zebrafish</name>
    <pose>Unspecified</pose>
    <truncated>1</truncated>
    <difficult>0</difficult>
    <bndbox>
      <xmin>639</xmin>
      <ymin>569</ymin>
      <xmax>849</xmax>
      <ymax>653</ymax>
    </bndbox>
  </object>
  <object>
    <name>Zebrafish</name>
    <pose>Unspecified</pose>
    <truncated>1</truncated>
    <difficult>0</difficult>
    <bndbox>
      <xmin>576</xmin>
      <ymin>497</ymin>
      <xmax>709</xmax>
      <ymax>623</ymax>
    </bndbox>
  </object>
</annotation>
