<annotation>
  <folder>Zebrafish-01-T</folder>
  <filename>000046.jpg</filename>
  <size>
    <width>2704</width>
    <height>1520</height>
    <depth>3</depth>
  </size>
  <object>
    <name>Zebrafish</name>
    <pose>Unspecified</pose>
    <truncated>0</truncated>
    <difficult>0</difficult>
    <bndbox>
      <xmin>1529</xmin>
      <ymin>1177</ymin>
      <xmax>1608</xmax>
      <ymax>1301</ymax>
    </bndbox>
  </object>
  <object>
    <name>Zebrafish</name>
    <pose>Unspecified</pose>
    <truncated>0</truncated>
    <difficult>0</difficult>
    <bndbox>
      <xmin>1397</xmin>
      <ymin>1202</ymin>
      <xmax>1515</xmax>
      <ymax>1307</ymax>
    </bndbox>
  </object>
</annotation>
