<annotation>
  <folder>Zebrafish-01-T</folder>
  <filename>002521.jpg</filename>
  <size>
    <width>2704</width>
    <height>1520</height>
    <depth>3</depth>
  </size>
  <object>
    <name>Zebrafish</name>
    <pose>Unspecified</pose>
    <truncated>0</truncated>
    <difficult>0</difficult>
    <bndbox>
      <xmin>1696</xmin>
      <ymin>1146</ymin>
      <xmax>1819</xmax>
      <ymax>1259</ymax>
    </bndbox>
  </object>
  <object>
    <name>Zebrafish</name>
    <pose>Unspecified</pose>
    <truncated>0</truncated>
    <difficult>0</difficult>
    <bndbox>
      <xmin>1708</xmin>
      <ymin>966</ymin>
      <xmax>1809</xmax>
      <ymax>1070</ymax>
    </bndbox>
  </object>
</annotation>
