<annotation>
  <folder>Zebrafish-01-T</folder>
  <filename>002740.jpg</filename>
  <size>
    <width>2704</width>
    <height>1520</height>
    <depth>3</depth>
  </size>
  <object>
    <name>Zebrafish</name>
    <pose>Unspecified</pose>
    <truncated>0</truncated>
    <difficult>0</difficult>
    <bndbox>
      <xmin>1671</xmin>
      <ymin>1108</ymin>
      <xmax>1756</xmax>
      <ymax>1249</ymax>
    </bndbox>
  </object>
  <object>
    <name>Zebrafish</name>
    <pose>Unspecified</pose>
    <truncated>0</truncated>
    <difficult>0</difficult>
    <bndbox>
      <xmin>1741</xmin>
      <ymin>1044</ymin>
      <xmax>1770</xmax>
      <ymax>1193</ymax>
    </bndbox>
  </object>
</annotation>
