<annotation>
  <folder>Zebrafish-01-T</folder>
  <filename>002889.jpg</filename>
  <size>
    <width>2704</width>
    <height>1520</height>
    <depth>3</depth>
  </size>
  <object>
    <name>Zebrafish</name>
    <pose>Unspecified</pose>
    <truncated>1</truncated>
    <difficult>0</difficult>
    <bndbox>
      <xmin>1681</xmin>
      <ymin>345</ymin>
      <xmax>1756</xmax>
      <ymax>463</ymax>
    </bndbox>
  </object>
  <object>
    <name>Zebrafish</name>
    <pose>Unspecified</pose>
    <truncated>1</truncated>
    <difficult>0</difficult>
    <bndbox>
      <xmin>1680</xmin>
      <ymin>430</ymin>
      <xmax>1829</xmax>
      <ymax>485</ymax>
    </bndbox>
  </object>
</annotation>
