<annotation>
  <folder>Zebrafish-01-T</folder>
  <filename>002884.jpg</filename>
  <size>
    <width>2704</width>
    <height>1520</height>
    <depth>3</depth>
  </size>
  <object>
    <name>Zebrafish</name>
    <pose>Unspecified</pose>
    <truncated>1</truncated>
    <difficult>0</difficult>
    <bndbox>
      <xmin>1675</xmin>
      <ymin>353</ymin>
      <xmax>1768</xmax>
      <ymax>457</ymax>
    </bndbox>
  </object>
  <object>
    <name>Zebrafish</name>
    <pose>Unspecified</pose>
    <truncated>1</truncated>
    <difficult>0</difficult>
    <bndbox>
      <xmin>1694</xmin>
      <ymin>434</ymin>
      <xmax>1845</xmax>
      <ymax>482</ymax>
    </bndbox>
  </object>
</annotation>
