<annotation>
  <folder>Zebrafish-01-T</folder>
  <filename>002840.jpg</filename>
  <size>
    <width>2704</width>
    <height>1520</height>
    <depth>3</depth>
  </size>
  <object>
    <name>Zebrafish</name>
    <pose>Unspecified</pose>
    <truncated>0</truncated>
    <difficult>0</difficult>
    <bndbox>
      <xmin>1683</xmin>
      <ymin>505</ymin>
      <xmax>1717</xmax>
      <ymax>655</ymax>
    </bndbox>
  </object>
  <object>
    <name>Zebrafish</name>
    <pose>Unspecified</pose>
    <truncated>0</truncated>
    <difficult>0</difficult>
    <bndbox>
      <xmin>1691</xmin>
      <ymin>379</ymin>
      <xmax>1768</xmax>
      <ymax>485</ymax>
    </bndbox>
  </object>
</annotation>
