<annotation>
  <folder>Zebrafish-01-T</folder>
  <filename>002977.jpg</filename>
  <size>
    <width>2704</width>
    <height>1520</height>
    <depth>3</depth>
  </size>
  <object>
    <name>Zebrafish</name>
    <pose>Unspecified</pose>
    <truncated>0</truncated>
    <difficult>0</difficult>
    <bndbox>
      <xmin>1648</xmin>
      <ymin>491</ymin>
      <xmax>1739</xmax>
      <ymax>631</ymax>
    </bndbox>
  </object>
  <object>
    <name>Zebrafish</name>
    <pose>Unspecified</pose>
    <truncated>0</truncated>
    <difficult>0</difficult>
    <bndbox>
      <xmin>1739</xmin>
      <ymin>389</ymin>
      <xmax>1816</xmax>
      <ymax>529</ymax>
    </bndbox>
  </object>
</annotation>
