<annotation>
  <folder>Zebrafish-01-T</folder>
  <filename>002953.jpg</filename>
  <size>
    <width>2704</width>
    <height>1520</height>
    <depth>3</depth>
  </size>
  <object>
    <name>Zebrafish</name>
    <pose>Unspecified</pose>
    <truncated>0</truncated>
    <difficult>0</difficult>
    <bndbox>
      <xmin>1675</xmin>
      <ymin>473</ymin>
      <xmax>1744</xmax>
      <ymax>585</ymax>
    </bndbox>
  </object>
  <object>
    <name>Zebrafish</name>
    <pose>Unspecified</pose>
    <truncated>0</truncated>
    <difficult>0</difficult>
    <bndbox>
      <xmin>1766</xmin>
      <ymin>311</ymin>
      <xmax>1814</xmax>
      <ymax>457</ymax>
    </bndbox>
  </object>
</annotation>
