<annotation>
  <folder>Zebrafish-01-T</folder>
  <filename>003189.jpg</filename>
  <size>
    <width>2704</width>
    <height>1520</height>
    <depth>3</depth>
  </size>
  <object>
    <name>Zebrafish</name>
    <pose>Unspecified</pose>
    <truncated>0</truncated>
    <difficult>0</difficult>
    <bndbox>
      <xmin>1549</xmin>
      <ymin>939</ymin>
      <xmax>1614</xmax>
      <ymax>1110</ymax>
    </bndbox>
  </object>
  <object>
    <name>Zebrafish</name>
    <pose>Unspecified</pose>
    <truncated>0</truncated>
    <difficult>0</difficult>
    <bndbox>
      <xmin>1631</xmin>
      <ymin>838</ymin>
      <xmax>1739</xmax>
      <ymax>974</ymax>
    </bndbox>
  </object>
</annotation>
