<annotation>
  <folder>Zebrafish-01-T</folder>
  <filename>003595.jpg</filename>
  <size>
    <width>2704</width>
    <height>1520</height>
    <depth>3</depth>
  </size>
  <object>
    <name>Zebrafish</name>
    <pose>Unspecified</pose>
    <truncated>0</truncated>
    <difficult>0</difficult>
    <bndbox>
      <xmin>1424</xmin>
      <ymin>815</ymin>
      <xmax>1574</xmax>
      <ymax>868</ymax>
    </bndbox>
  </object>
  <object>
    <name>Zebrafish</name>
    <pose>Unspecified</pose>
    <truncated>0</truncated>
    <difficult>0</difficult>
    <bndbox>
      <xmin>1310</xmin>
      <ymin>902</ymin>
      <xmax>1362</xmax>
      <ymax>1049</ymax>
    </bndbox>
  </object>
</annotation>
