<annotation>
  <folder>Zebrafish-01-T</folder>
  <filename>003937.jpg</filename>
  <size>
    <width>2704</width>
    <height>1520</height>
    <depth>3</depth>
  </size>
  <object>
    <name>Zebrafish</name>
    <pose>Unspecified</pose>
    <truncated>0</truncated>
    <difficult>0</difficult>
    <bndbox>
      <xmin>950</xmin>
      <ymin>1095</ymin>
      <xmax>996</xmax>
      <ymax>1260</ymax>
    </bndbox>
  </object>
  <object>
    <name>Zebrafish</name>
    <pose>Unspecified</pose>
    <truncated>0</truncated>
    <difficult>0</difficult>
    <bndbox>
      <xmin>996</xmin>
      <ymin>999</ymin>
      <xmax>1067</xmax>
      <ymax>1165</ymax>
    </bndbox>
  </object>
</annotation>
