<annotation>
  <folder>Zebrafish-01-T</folder>
  <filename>004401.jpg</filename>
  <size>
    <width>2704</width>
    <height>1520</height>
    <depth>3</depth>
  </size>
  <object>
    <name>Zebrafish</name>
    <pose>Unspecified</pose>
    <truncated>1</truncated>
    <difficult>0</difficult>
    <bndbox>
      <xmin>970</xmin>
      <ymin>1195</ymin>
      <xmax>1062</xmax>
      <ymax>1337</ymax>
    </bndbox>
  </object>
  <object>
    <name>Zebrafish</name>
    <pose>Unspecified</pose>
    <truncated>1</truncated>
    <difficult>0</difficult>
    <bndbox>
      <xmin>1032</xmin>
      <ymin>1191</ymin>
      <xmax>1121</xmax>
      <ymax>1310</ymax>
    </bndbox>
  </object>
</annotation>
