<annotation>
  <folder>Zebrafish-01-T</folder>
  <filename>005079.jpg</filename>
  <size>
    <width>2704</width>
    <height>1520</height>
    <depth>3</depth>
  </size>
  <object>
    <name>Zebrafish</name>
    <pose>Unspecified</pose>
    <truncated>1</truncated>
    <difficult>0</difficult>
    <bndbox>
      <xmin>860</xmin>
      <ymin>1146</ymin>
      <xmax>932</xmax>
      <ymax>1261</ymax>
    </bndbox>
  </object>
  <object>
    <name>Zebrafish</name>
    <pose>Unspecified</pose>
    <truncated>1</truncated>
    <difficult>0</difficult>
    <bndbox>
      <xmin>900</xmin>
      <ymin>1176</ymin>
      <xmax>1030</xmax>
      <ymax>1228</ymax>
    </bndbox>
  </object>
</annotation>
