<annotation>
  <folder>Zebrafish-01-T</folder>
  <filename>005970.jpg</filename>
  <size>
    <width>2704</width>
    <height>1520</height>
    <depth>3</depth>
  </size>
  <object>
    <name>Zebrafish</name>
    <pose>Unspecified</pose>
    <truncated>0</truncated>
    <difficult>0</difficult>
    <bndbox>
      <xmin>1122</xmin>
      <ymin>746</ymin>
      <xmax>1216</xmax>
      <ymax>868</ymax>
    </bndbox>
  </object>
  <object>
    <name>Zebrafish</name>
    <pose>Unspecified</pose>
    <truncated>0</truncated>
    <difficult>0</difficult>
    <bndbox>
      <xmin>1247</xmin>
      <ymin>787</ymin>
      <xmax>1371</xmax>
      <ymax>912</ymax>
    </bndbox>
  </object>
</annotation>
