<annotation>
  <folder>Zebrafish-01-T</folder>
  <filename>005987.jpg</filename>
  <size>
    <width>2704</width>
    <height>1520</height>
    <depth>3</depth>
  </size>
  <object>
    <name>Zebrafish</name>
    <pose>Unspecified</pose>
    <truncated>0</truncated>
    <difficult>0</difficult>
    <bndbox>
      <xmin>1074</xmin>
      <ymin>660</ymin>
      <xmax>1151</xmax>
      <ymax>806</ymax>
    </bndbox>
  </object>
  <object>
    <name>Zebrafish</name>
    <pose>Unspecified</pose>
    <truncated>0</truncated>
    <difficult>0</difficult>
    <bndbox>
      <xmin>1187</xmin>
      <ymin>720</ymin>
      <xmax>1300</xmax>
      <ymax>851</ymax>
    </bndbox>
  </object>
</annotation>
