<annotation>
  <folder>Zebrafish-02-T</folder>
  <filename>000200.jpg</filename>
  <size>
    <width>2704</width>
    <height>1520</height>
    <depth>3</depth>
  </size>
  <object>
    <name>Zebrafish</name>
    <pose>Unspecified</pose>
    <truncated>0</truncated>
    <difficult>0</difficult>
    <bndbox>
      <xmin>1042</xmin>
      <ymin>1075</ymin>
      <xmax>1116</xmax>
      <ymax>1222</ymax>
    </bndbox>
  </object>
  <object>
    <name>Zebrafish</name>
    <pose>Unspecified</pose>
    <truncated>0</truncated>
    <difficult>0</difficult>
    <bndbox>
      <xmin>1293</xmin>
      <ymin>1080</ymin>
      <xmax>1342</xmax>
      <ymax>1251</ymax>
    </bndbox>
  </object>
  <object>
    <name>Zebrafish</name>
    <pose>Unspecified</pose>
    <truncated>1</truncated>
    <difficult>0</difficult>
    <bndbox>
      <xmin>1197</xmin>
      <ymin>1205</ymin>
      <xmax>1299</xmax>
      <ymax>1319</ymax>
    </bndbox>
  </object>
  <object>
    <name>Zebrafish</name>
    <pose>Unspecified</pose>
    <truncated>0</truncated>
    <difficult>0</difficult>
    <bndbox>
      <xmin>1406</xmin>
      <ymin>1092</ymin>
      <xmax>1566</xmax>
      <ymax>1164</ymax>
    </bndbox>
  </object>
  <object>
    <name>Zebrafish</name>
    <pose>Unspecified</pose>
    <truncated>1</truncated>
    <difficult>0</difficult>
    <bndbox>
      <xmin>1092</xmin>
      <ymin>1278</ymin>
      <xmax>1258</xmax>
      <ymax>1351</ymax>
    </bndbox>
  </object>
</annotation>
