<annotation>
  <folder>Zebrafish-02-T</folder>
  <filename>000256.jpg</filename>
  <size>
    <width>2704</width>
    <height>1520</height>
    <depth>3</depth>
  </size>
  <object>
    <name>Zebrafish</name>
    <pose>Unspecified</pose>
    <truncated>1</truncated>
    <difficult>0</difficult>
    <bndbox>
      <xmin>1160</xmin>
      <ymin>1233</ymin>
      <xmax>1310</xmax>
      <ymax>1353</ymax>
    </bndbox>
  </object>
  <object>
    <name>Zebrafish</name>
    <pose>Unspecified</pose>
    <truncated>1</truncated>
    <difficult>0</difficult>
    <bndbox>
      <xmin>1324</xmin>
      <ymin>1209</ymin>
      <xmax>1350</xmax>
      <ymax>1380</ymax>
    </bndbox>
  </object>
  <object>
    <name>Zebrafish</name>
    <pose>Unspecified</pose>
    <truncated>1</truncated>
    <difficult>0</difficult>
    <bndbox>
      <xmin>1262</xmin>
      <ymin>1269</ymin>
      <xmax>1414</xmax>
      <ymax>1299</ymax>
    </bndbox>
  </object>
  <object>
    <name>Zebrafish</name>
    <pose>Unspecified</pose>
    <truncated>0</truncated>
    <difficult>0</difficult>
    <bndbox>
      <xmin>1480</xmin>
      <ymin>1242</ymin>
      <xmax>1654</xmax>
      <ymax>1298</ymax>
    </bndbox>
  </object>
  <object>
    <name>Zebrafish</name>
    <pose>Unspecified</pose>
    <truncated>1</truncated>
    <difficult>0</difficult>
    <bndbox>
      <xmin>1282</xmin>
      <ymin>1301</ymin>
      <xmax>1456</xmax>
      <ymax>1356</ymax>
    </bndbox>
  </object>
</annotation>
