<annotation>
  <folder>Zebrafish-02-T</folder>
  <filename>000217.jpg</filename>
  <size>
    <width>2704</width>
    <height>1520</height>
    <depth>3</depth>
  </size>
  <object>
    <name>Zebrafish</name>
    <pose>Unspecified</pose>
    <truncated>0</truncated>
    <difficult>0</difficult>
    <bndbox>
      <xmin>1044</xmin>
      <ymin>1157</ymin>
      <xmax>1175</xmax>
      <ymax>1288</ymax>
    </bndbox>
  </object>
  <object>
    <name>Zebrafish</name>
    <pose>Unspecified</pose>
    <truncated>0</truncated>
    <difficult>0</difficult>
    <bndbox>
      <xmin>1308</xmin>
      <ymin>1104</ymin>
      <xmax>1349</xmax>
      <ymax>1288</ymax>
    </bndbox>
  </object>
  <object>
    <name>Zebrafish</name>
    <pose>Unspecified</pose>
    <truncated>1</truncated>
    <difficult>0</difficult>
    <bndbox>
      <xmin>1167</xmin>
      <ymin>1214</ymin>
      <xmax>1292</xmax>
      <ymax>1318</ymax>
    </bndbox>
  </object>
  <object>
    <name>Zebrafish</name>
    <pose>Unspecified</pose>
    <truncated>0</truncated>
    <difficult>0</difficult>
    <bndbox>
      <xmin>1507</xmin>
      <ymin>1069</ymin>
      <xmax>1579</xmax>
      <ymax>1243</ymax>
    </bndbox>
  </object>
  <object>
    <name>Zebrafish</name>
    <pose>Unspecified</pose>
    <truncated>1</truncated>
    <difficult>0</difficult>
    <bndbox>
      <xmin>1153</xmin>
      <ymin>1311</ymin>
      <xmax>1326</xmax>
      <ymax>1342</ymax>
    </bndbox>
  </object>
</annotation>
