<annotation>
  <folder>Zebrafish-02-T</folder>
  <filename>000476.jpg</filename>
  <size>
    <width>2704</width>
    <height>1520</height>
    <depth>3</depth>
  </size>
  <object>
    <name>Zebrafish</name>
    <pose>Unspecified</pose>
    <truncated>0</truncated>
    <difficult>0</difficult>
    <bndbox>
      <xmin>1316</xmin>
      <ymin>1121</ymin>
      <xmax>1386</xmax>
      <ymax>1260</ymax>
    </bndbox>
  </object>
  <object>
    <name>Zebrafish</name>
    <pose>Unspecified</pose>
    <truncated>0</truncated>
    <difficult>0</difficult>
    <bndbox>
      <xmin>1532</xmin>
      <ymin>1247</ymin>
      <xmax>1702</xmax>
      <ymax>1289</ymax>
    </bndbox>
  </object>
  <object>
    <name>Zebrafish</name>
    <pose>Unspecified</pose>
    <truncated>1</truncated>
    <difficult>0</difficult>
    <bndbox>
      <xmin>1380</xmin>
      <ymin>1237</ymin>
      <xmax>1532</xmax>
      <ymax>1277</ymax>
    </bndbox>
  </object>
  <object>
    <name>Zebrafish</name>
    <pose>Unspecified</pose>
    <truncated>0</truncated>
    <difficult>0</difficult>
    <bndbox>
      <xmin>1333</xmin>
      <ymin>891</ymin>
      <xmax>1516</xmax>
      <ymax>943</ymax>
    </bndbox>
  </object>
  <object>
    <name>Zebrafish</name>
    <pose>Unspecified</pose>
    <truncated>1</truncated>
    <difficult>0</difficult>
    <bndbox>
      <xmin>1403</xmin>
      <ymin>1149</ymin>
      <xmax>1483</xmax>
      <ymax>1271</ymax>
    </bndbox>
  </object>
</annotation>
