<annotation>
  <folder>Zebrafish-02-T</folder>
  <filename>000516.jpg</filename>
  <size>
    <width>2704</width>
    <height>1520</height>
    <depth>3</depth>
  </size>
  <object>
    <name>Zebrafish</name>
    <pose>Unspecified</pose>
    <truncated>0</truncated>
    <difficult>0</difficult>
    <bndbox>
      <xmin>1390</xmin>
      <ymin>1054</ymin>
      <xmax>1545</xmax>
      <ymax>1118</ymax>
    </bndbox>
  </object>
  <object>
    <name>Zebrafish</name>
    <pose>Unspecified</pose>
    <truncated>1</truncated>
    <difficult>0</difficult>
    <bndbox>
      <xmin>1428</xmin>
      <ymin>1211</ymin>
      <xmax>1559</xmax>
      <ymax>1312</ymax>
    </bndbox>
  </object>
  <object>
    <name>Zebrafish</name>
    <pose>Unspecified</pose>
    <truncated>1</truncated>
    <difficult>0</difficult>
    <bndbox>
      <xmin>1454</xmin>
      <ymin>1219</ymin>
      <xmax>1610</xmax>
      <ymax>1268</ymax>
    </bndbox>
  </object>
  <object>
    <name>Zebrafish</name>
    <pose>Unspecified</pose>
    <truncated>0</truncated>
    <difficult>0</difficult>
    <bndbox>
      <xmin>1518</xmin>
      <ymin>884</ymin>
      <xmax>1630</xmax>
      <ymax>1028</ymax>
    </bndbox>
  </object>
  <object>
    <name>Zebrafish</name>
    <pose>Unspecified</pose>
    <truncated>0</truncated>
    <difficult>0</difficult>
    <bndbox>
      <xmin>1334</xmin>
      <ymin>1195</ymin>
      <xmax>1452</xmax>
      <ymax>1285</ymax>
    </bndbox>
  </object>
</annotation>
