<annotation>
  <folder>Zebrafish-02-T</folder>
  <filename>000677.jpg</filename>
  <size>
    <width>2704</width>
    <height>1520</height>
    <depth>3</depth>
  </size>
  <object>
    <name>Zebrafish</name>
    <pose>Unspecified</pose>
    <truncated>1</truncated>
    <difficult>0</difficult>
    <bndbox>
      <xmin>1397</xmin>
      <ymin>1179</ymin>
      <xmax>1552</xmax>
      <ymax>1229</ymax>
    </bndbox>
  </object>
  <object>
    <name>Zebrafish</name>
    <pose>Unspecified</pose>
    <truncated>1</truncated>
    <difficult>0</difficult>
    <bndbox>
      <xmin>1612</xmin>
      <ymin>1072</ymin>
      <xmax>1717</xmax>
      <ymax>1182</ymax>
    </bndbox>
  </object>
  <object>
    <name>Zebrafish</name>
    <pose>Unspecified</pose>
    <truncated>1</truncated>
    <difficult>0</difficult>
    <bndbox>
      <xmin>1476</xmin>
      <ymin>1210</ymin>
      <xmax>1607</xmax>
      <ymax>1268</ymax>
    </bndbox>
  </object>
  <object>
    <name>Zebrafish</name>
    <pose>Unspecified</pose>
    <truncated>1</truncated>
    <difficult>0</difficult>
    <bndbox>
      <xmin>1423</xmin>
      <ymin>1093</ymin>
      <xmax>1473</xmax>
      <ymax>1267</ymax>
    </bndbox>
  </object>
  <object>
    <name>Zebrafish</name>
    <pose>Unspecified</pose>
    <truncated>1</truncated>
    <difficult>0</difficult>
    <bndbox>
      <xmin>1606</xmin>
      <ymin>1167</ymin>
      <xmax>1704</xmax>
      <ymax>1275</ymax>
    </bndbox>
  </object>
</annotation>
