<annotation>
  <folder>Zebrafish-02-T</folder>
  <filename>000609.jpg</filename>
  <size>
    <width>2704</width>
    <height>1520</height>
    <depth>3</depth>
  </size>
  <object>
    <name>Zebrafish</name>
    <pose>Unspecified</pose>
    <truncated>1</truncated>
    <difficult>0</difficult>
    <bndbox>
      <xmin>1561</xmin>
      <ymin>1124</ymin>
      <xmax>1685</xmax>
      <ymax>1221</ymax>
    </bndbox>
  </object>
  <object>
    <name>Zebrafish</name>
    <pose>Unspecified</pose>
    <truncated>1</truncated>
    <difficult>0</difficult>
    <bndbox>
      <xmin>1561</xmin>
      <ymin>1217</ymin>
      <xmax>1678</xmax>
      <ymax>1286</ymax>
    </bndbox>
  </object>
  <object>
    <name>Zebrafish</name>
    <pose>Unspecified</pose>
    <truncated>1</truncated>
    <difficult>0</difficult>
    <bndbox>
      <xmin>1406</xmin>
      <ymin>1236</ymin>
      <xmax>1551</xmax>
      <ymax>1283</ymax>
    </bndbox>
  </object>
  <object>
    <name>Zebrafish</name>
    <pose>Unspecified</pose>
    <truncated>1</truncated>
    <difficult>0</difficult>
    <bndbox>
      <xmin>1490</xmin>
      <ymin>1244</ymin>
      <xmax>1677</xmax>
      <ymax>1287</ymax>
    </bndbox>
  </object>
  <object>
    <name>Zebrafish</name>
    <pose>Unspecified</pose>
    <truncated>1</truncated>
    <difficult>0</difficult>
    <bndbox>
      <xmin>1447</xmin>
      <ymin>1253</ymin>
      <xmax>1595</xmax>
      <ymax>1279</ymax>
    </bndbox>
  </object>
</annotation>
