<annotation>
  <folder>Zebrafish-02-T</folder>
  <filename>000726.jpg</filename>
  <size>
    <width>2704</width>
    <height>1520</height>
    <depth>3</depth>
  </size>
  <object>
    <name>Zebrafish</name>
    <pose>Unspecified</pose>
    <truncated>0</truncated>
    <difficult>0</difficult>
    <bndbox>
      <xmin>1407</xmin>
      <ymin>1081</ymin>
      <xmax>1555</xmax>
      <ymax>1138</ymax>
    </bndbox>
  </object>
  <object>
    <name>Zebrafish</name>
    <pose>Unspecified</pose>
    <truncated>0</truncated>
    <difficult>0</difficult>
    <bndbox>
      <xmin>1619</xmin>
      <ymin>1011</ymin>
      <xmax>1742</xmax>
      <ymax>1038</ymax>
    </bndbox>
  </object>
  <object>
    <name>Zebrafish</name>
    <pose>Unspecified</pose>
    <truncated>0</truncated>
    <difficult>0</difficult>
    <bndbox>
      <xmin>1563</xmin>
      <ymin>1199</ymin>
      <xmax>1705</xmax>
      <ymax>1259</ymax>
    </bndbox>
  </object>
  <object>
    <name>Zebrafish</name>
    <pose>Unspecified</pose>
    <truncated>0</truncated>
    <difficult>0</difficult>
    <bndbox>
      <xmin>1453</xmin>
      <ymin>901</ymin>
      <xmax>1502</xmax>
      <ymax>1082</ymax>
    </bndbox>
  </object>
  <object>
    <name>Zebrafish</name>
    <pose>Unspecified</pose>
    <truncated>0</truncated>
    <difficult>0</difficult>
    <bndbox>
      <xmin>1668</xmin>
      <ymin>1075</ymin>
      <xmax>1710</xmax>
      <ymax>1222</ymax>
    </bndbox>
  </object>
</annotation>
