<annotation>
  <folder>Zebrafish-02-T</folder>
  <filename>000839.jpg</filename>
  <size>
    <width>2704</width>
    <height>1520</height>
    <depth>3</depth>
  </size>
  <object>
    <name>Zebrafish</name>
    <pose>Unspecified</pose>
    <truncated>0</truncated>
    <difficult>0</difficult>
    <bndbox>
      <xmin>1604</xmin>
      <ymin>975</ymin>
      <xmax>1712</xmax>
      <ymax>1095</ymax>
    </bndbox>
  </object>
  <object>
    <name>Zebrafish</name>
    <pose>Unspecified</pose>
    <truncated>0</truncated>
    <difficult>0</difficult>
    <bndbox>
      <xmin>1631</xmin>
      <ymin>803</ymin>
      <xmax>1718</xmax>
      <ymax>932</ymax>
    </bndbox>
  </object>
  <object>
    <name>Zebrafish</name>
    <pose>Unspecified</pose>
    <truncated>0</truncated>
    <difficult>0</difficult>
    <bndbox>
      <xmin>1448</xmin>
      <ymin>1209</ymin>
      <xmax>1574</xmax>
      <ymax>1284</ymax>
    </bndbox>
  </object>
  <object>
    <name>Zebrafish</name>
    <pose>Unspecified</pose>
    <truncated>0</truncated>
    <difficult>0</difficult>
    <bndbox>
      <xmin>1455</xmin>
      <ymin>454</ymin>
      <xmax>1483</xmax>
      <ymax>625</ymax>
    </bndbox>
  </object>
  <object>
    <name>Zebrafish</name>
    <pose>Unspecified</pose>
    <truncated>0</truncated>
    <difficult>0</difficult>
    <bndbox>
      <xmin>1586</xmin>
      <ymin>1069</ymin>
      <xmax>1641</xmax>
      <ymax>1202</ymax>
    </bndbox>
  </object>
</annotation>
