<annotation>
  <folder>Zebrafish-02-T</folder>
  <filename>000818.jpg</filename>
  <size>
    <width>2704</width>
    <height>1520</height>
    <depth>3</depth>
  </size>
  <object>
    <name>Zebrafish</name>
    <pose>Unspecified</pose>
    <truncated>0</truncated>
    <difficult>0</difficult>
    <bndbox>
      <xmin>1674</xmin>
      <ymin>1044</ymin>
      <xmax>1745</xmax>
      <ymax>1181</ymax>
    </bndbox>
  </object>
  <object>
    <name>Zebrafish</name>
    <pose>Unspecified</pose>
    <truncated>0</truncated>
    <difficult>0</difficult>
    <bndbox>
      <xmin>1668</xmin>
      <ymin>859</ymin>
      <xmax>1766</xmax>
      <ymax>965</ymax>
    </bndbox>
  </object>
  <object>
    <name>Zebrafish</name>
    <pose>Unspecified</pose>
    <truncated>0</truncated>
    <difficult>0</difficult>
    <bndbox>
      <xmin>1454</xmin>
      <ymin>1219</ymin>
      <xmax>1590</xmax>
      <ymax>1291</ymax>
    </bndbox>
  </object>
  <object>
    <name>Zebrafish</name>
    <pose>Unspecified</pose>
    <truncated>0</truncated>
    <difficult>0</difficult>
    <bndbox>
      <xmin>1456</xmin>
      <ymin>509</ymin>
      <xmax>1484</xmax>
      <ymax>680</ymax>
    </bndbox>
  </object>
  <object>
    <name>Zebrafish</name>
    <pose>Unspecified</pose>
    <truncated>0</truncated>
    <difficult>0</difficult>
    <bndbox>
      <xmin>1562</xmin>
      <ymin>1007</ymin>
      <xmax>1627</xmax>
      <ymax>1153</ymax>
    </bndbox>
  </object>
</annotation>
